censusbatchgeocoder/__init__.py
censusbatchgeocoder-0.1.1.dist-info/LICENSE
censusbatchgeocoder-0.1.1.dist-info/METADATA
censusbatchgeocoder-0.1.1.dist-info/WHEEL
censusbatchgeocoder-0.1.1.dist-info/top_level.txt
censusbatchgeocoder-0.1.1.dist-info/RECORD
