Metadata-Version: 2.1
Name: censusbatchgeocoder
Version: 0.1.1
Summary: A simple Python wrapper for the U.S. Census Geocoding Services API batch service
Home-page: http://www.github.com/palewire/censusbatchgeocoder/
Author: Ben Welsh
Author-email: b@palewi.re
License: MIT
Project-URL: Documentation, http://palewi.re/docs/censusbatchgeocoder
Project-URL: Source, https://github.com/palewire/censusbatchgeocoder
Project-URL: Tracker, https://github.com/palewire/censusbatchgeocoder/issues
Classifier: Development Status :: 5 - Production/Stable
Classifier: Intended Audience :: Developers
Classifier: Operating System :: OS Independent
Classifier: License :: OSI Approved :: MIT License
Classifier: Programming Language :: Python
Classifier: Programming Language :: Python :: 3
Classifier: Programming Language :: Python :: 3.9
Classifier: Programming Language :: Python :: 3.10
Classifier: Programming Language :: Python :: 3.11
Classifier: Topic :: Internet :: WWW/HTTP
License-File: LICENSE
Requires-Dist: requests
Requires-Dist: agate >=1.6.0
